picus/__init__.py
picus/picus.py
picus/core/__init__.py
picus/core/evidencecollection.py
picus/core/variantclassification.py
picus/data/BP1.tsv
picus/data/PP2.tsv
picus/data/PS4.tsv
picus/data/__init__.py
picus/data/clinvar.csv
picus/data/lof_genes.tsv
picus/data/variant_consequences.tsv
picus/example/__init__.py
picus/example/variant_data.json
picus/templates/__init__.py
picus/templates/picus.png
picus/templates/report_data.json
picus/templates/template.Rnw
picus/tests/__init__.py
picus/tests/test.py
picus/utils/__init__.py
picus/utils/createreport.py
picus/utils/download.py
picus/utils/tabix.py
picus-0.0.5.dist-info/LICENSE
picus-0.0.5.dist-info/METADATA
picus-0.0.5.dist-info/WHEEL
picus-0.0.5.dist-info/entry_points.txt
picus-0.0.5.dist-info/top_level.txt
picus-0.0.5.dist-info/RECORD
