Metadata-Version: 2.1
Name: picus
Version: 0.0.5
Summary: Pointed Interpretation of Clinical Variant Significance
Home-page: UNKNOWN
Author: bars
Author-email: barslmn@gmail.com
License: UNKNOWN
Keywords: genomics next generation sequencing variant classification human genetics
Platform: UNKNOWN
Classifier: Development Status :: 3 - Alpha
Classifier: Intended Audience :: Developers
Classifier: Topic :: Software Development :: Build Tools
Classifier: License :: OSI Approved :: MIT License
Classifier: Programming Language :: Python :: 3
Requires-Dist: pandas
